poordub/__init__.py
poordub-0.1.4.dist-info/LICENSE.txt
poordub-0.1.4.dist-info/METADATA
poordub-0.1.4.dist-info/WHEEL
poordub-0.1.4.dist-info/top_level.txt
poordub-0.1.4.dist-info/RECORD
