Metadata-Version: 2.1
Name: poordub
Version: 0.1.4
Summary: A minimalistic audio processing library
Home-page: https://github.com/dnknth/poordub
Author: dnknth
License: UNKNOWN
Platform: UNKNOWN
Classifier: License :: OSI Approved :: MIT License
Classifier: Operating System :: OS Independent
Classifier: Development Status :: 3 - Alpha
Classifier: Intended Audience :: Developers
Classifier: Programming Language :: Python :: 3 :: Only
Classifier: Topic :: Multimedia :: Sound/Audio
Classifier: Topic :: Software Development :: Libraries
License-File: LICENSE.txt
Requires-Dist: setuptools
